TEF/__init__.py
TEF/__main__.py
TEF/auto_set_dtypes.py
TEF/dfmeta.py
TEF/fit.py
TEF/plot_1var.py
TEF/plot_1var_by_cat_y.py
TEF/util.py
TEF/version.py
TEF/TEF/__init__.py
TEF/TEF/auto_set_dtypes.py
TEF/TEF/dfmeta.py
TEF/TEF/fit.py
TEF/TEF/plot_1var.py
TEF/TEF/plot_1var_by_cat_y.py
TEF/TEF/util.py
TEF-0.9.1.dist-info/LICENSE.txt
TEF-0.9.1.dist-info/METADATA
TEF-0.9.1.dist-info/WHEEL
TEF-0.9.1.dist-info/top_level.txt
TEF-0.9.1.dist-info/RECORD
