Metadata-Version: 2.1
Name: TEF
Version: 0.9.1
Summary: tll549's Exploratory Functions
Home-page: https://github.com/tll549/TEF
Author: tll549
Author-email: el@tll.tl
License: UNKNOWN
Platform: UNKNOWN
Classifier: Programming Language :: Python :: 3
Classifier: License :: OSI Approved :: MIT License
Classifier: Operating System :: OS Independent
